Metadata-Version: 1.1
Name: ptolemy
Version: 1.0.0
Summary: Write terse AWS DMS table mappings.
Home-page: https://github.com/cloudreach/ptolemy
Author: James Routley
Author-email: jroutley@gmail.com
License: Apache Software License 2.0
Keywords: ptolemy
Platform: UNKNOWN
Classifier: Development Status :: 2 - Pre-Alpha
Classifier: Intended Audience :: Developers
Classifier: License :: OSI Approved :: Apache Software License
Classifier: Natural Language :: English
Classifier: Programming Language :: Python :: 2
Classifier: Programming Language :: Python :: 2.7
Classifier: Programming Language :: Python :: 3
Classifier: Programming Language :: Python :: 3.3
Classifier: Programming Language :: Python :: 3.4
Classifier: Programming Language :: Python :: 3.5
Classifier: Programming Language :: Python :: 3.6
